vppppppp/__init__.py
vppppppp/core.py
vppppppp/log.py
vppppppp/server.py
vppppppp-0.1.1.dist-info/METADATA
vppppppp-0.1.1.dist-info/WHEEL
vppppppp-0.1.1.dist-info/top_level.txt
vppppppp-0.1.1.dist-info/RECORD
